{
  "asin_from_details": "B01E94R21W",
  "title": "Dishwasher diskette assorted trendy Kitchen accessories",
  "current_price": 5.08,
  "main_image": "https://m.media-amazon.com/images/W/MEDIAX_1215821-T2/images/I/61w7Z1te-rL._AC_SL1500_.jpg",
  "thumbnails": [
    "https://m.media-amazon.com/images/W/MEDIAX_1215821-T2/images/I/41Xf+B6s+LL._AC_SR38,50_.jpg",
    "https://m.media-amazon.com/images/W/MEDIAX_1215821-T2/images/I/31hacrw1rSL._AC_SR38,50_.jpg",
    "https://m.media-amazon.com/images/W/MEDIAX_1215821-T2/images/I/31spnAufOIL._AC_SR38,50_.jpg"
  ],
  "high_res_gallery": [],
  "amazon_product_details_section": {
    "ASIN": "B01E94R21W",
    "Date First Available": "5 Feb. 2017"
  },
  "date_first_available_from_details": "5 Feb. 2017",
  "prime_eligible": false,
  "fulfilled_by_amazon": false,
  "seller_info_text": "FINCHLEY ENTERPRISE",
  "sold_by_amazon": false,
  "rating": 5.0,
  "availability_text": "In stock",
  "in_stock": true,
  "specifications_table": {
    "Model": "‎8017904262122",
    "Package Dimensions": "‎21 x 6 x 4 cm; 100 g",
    "Material Type": "‎Acrylonitrile Butadiene Styrene (ABS)",
    "Included Components": "‎Dishwasher",
    "Batteries Required?": "‎No",
    "Item Weight": "‎100 g"
  },
  "selleramp": {
    "status": "SellerAmp extraction disabled"
  },
  "keepa": {
    "status": "Extraction process completed",
    "ai_graph_analysis_status": "Keepa Graph AI Analysis disabled",
    "product_details_tab_data": {
      "Title": "Dishwasher diskette assorted trendy Kitchen accessories",
      "Last Price Change": "just now",
      "Buy Box Seller": "FINCHLEY ENTERPRISE (85% positive over last 12 months)",
      "FBA Pick&Pack Fee": 2.42,
      "Referral Fee %": "15 %",
      "Referral Fee based on current Buy Box price": 0.76,
      "Lowest FBM Seller": "The Other Place Gift & Hardware (70% positive over last 12 months)",
      "Total Offer Count": "2",
      "Tracking since": "2018/09/10",
      "Listed since": "2017/02/05",
      "Categories - Root": "Home & Kitchen",
      "Categories - Sub": "Household Appliances / Categories",
      "Categories - Tree": "Home & Kitchen › Kitchen & Home Appliances › Household Appliances",
      "Website Display Group - Name": "Major Appliances",
      "ASIN": "B01E94R21W",
      "Product Codes - EAN": "8017904262122",
      "Type": "CLEANING_BRUSH",
      "Product Group": "Major Appliances",
      "Model": "8017904262122",
      "Unit Details - Unit Value": "1",
      "Unit Details - Unit Type": "Unit",
      "Material": "Acrylonitrile Butadiene Styrene (ABS)",
      "Specific Uses": "Dishwasher",
      "Binding": "Kitchen & Home",
      "Number of Items": "1",
      "Package - Dimension (cm³)": "21.0 x 6.0 x 4.0 cm (= 504 cm³ )",
      "Package - Weight (g)": "100",
      "Package - Quantity": "1",
      "Included Components": "Dishwasher"
    }
  },
  "eans_on_page": [
    "8017904262122"
  ],
  "ean_on_page_source": "Keepa_Product_Details",
  "ean_on_page": "8017904262122",
  "asin_extracted_from_page": "B01E94R21W",
  "asin_queried": "B01E94R21W",
  "asin": "B01E94R21W"
}