{
  "asin_from_details": "B06Y36ZVPZ",
  "title": "Jeylly for iPhone 5/5S/SE Case, [3 Color] Slim Hybrid Impact Rugged Soft TPU & Hard PC Bumper Shockproof Protective Anti-slip Case Cover Shell for iPhone 5/5s/SE - Green",
  "current_price": 8.54,
  "original_price": 8.99,
  "main_image": "https://m.media-amazon.com/images/W/MEDIAX_1215821-T2/images/I/81zFa3qmC+L._AC_SL1500_.jpg",
  "thumbnails": [
    "https://m.media-amazon.com/images/W/MEDIAX_1215821-T2/images/I/51cqQKNCuEL._SL1500_.jpg",
    "https://m.media-amazon.com/images/W/MEDIAX_1215821-T2/images/I/51q-4MeqFqL._SL1500_.jpg",
    "https://m.media-amazon.com/images/W/MEDIAX_1215821-T2/images/I/51jyMuo4xNL._SL1500_.jpg",
    "https://m.media-amazon.com/images/W/MEDIAX_1215821-T2/images/I/61GCTm6dWIL._SL1500_.jpg",
    "https://m.media-amazon.com/images/W/MEDIAX_1215821-T2/images/I/51las8BU70L._SL1500_.jpg",
    "https://m.media-amazon.com/images/W/MEDIAX_1215821-T2/images/I/51DeN8kTGUL._SL1500_.jpg",
    "https://m.media-amazon.com/images/W/MEDIAX_1215821-T2/images/I/31TTVYf4llL._SL1500_.jpg"
  ],
  "high_res_gallery": [],
  "amazon_product_details_section": {
    "Is discontinued by manufacturer\n                                    ‏\n                                    :\n                                    ‎": "No",
    "Product Dimensions\n                                    ‏\n                                    :\n                                    ‎": "14.73 x 5.84 x 0.76 cm; 18 g",
    "Date First Available\n                                    ‏\n                                    :\n                                    ‎": "4 Jun. 2018",
    "Manufacturer\n                                    ‏\n                                    :\n                                    ‎": "Jeylly",
    "ASIN\n                                    ‏\n                                    :\n                                    ‎": "B06Y36ZVPZ",
    "Item model number\n                                    ‏\n                                    :\n                                    ‎": "5/5S/SE 2016",
    "Country of origin\n                                    ‏\n                                    :\n                                    ‎": "China",
    "Guaranteed software updates until\n                                    ‏\n                                    :\n                                    ‎": "unknown",
    "Customer reviews": "4.2 4.2 out of 5 stars (2,081) var dpAcrHasRegisteredArcLinkClickAction; P.when('A', 'ready').execute(function(A) { if (dpAcrHasRegisteredArcLinkClickAction !== true) { dpAcrHasRegisteredArcLinkClickAction = true; A.declarative( 'acrLink-click-metrics', 'click', { \"allowLinkDefault\": true }, function (event) { if (window.ue) { ue.count(\"acrLinkClickCount\", (ue.count(\"acrLinkClickCount\") || 0) + 1); } } ); } }); P.when('A', 'cf').execute(function(A) { A.declarative('acrStarsLink-click-metrics', 'click', { \"allowLinkDefault\" : true }, function(event){ if(window.ue) { ue.count(\"acrStarsLinkWithPopoverClickCount\", (ue.count(\"acrStarsLinkWithPopoverClickCount\") || 0) + 1); } }); });",
    "Is discontinued by manufacturer\n                                    ‏": "‎ No",
    "Product Dimensions\n                                    ‏": "‎ 14.73 x 5.84 x 0.76 cm; 18 g",
    "Date First Available\n                                    ‏": "‎ 4 Jun. 2018",
    "Manufacturer\n                                    ‏": "‎ Jeylly",
    "ASIN\n                                    ‏": "‎ B06Y36ZVPZ",
    "Item model number\n                                    ‏": "‎ 5/5S/SE 2016",
    "Country of origin\n                                    ‏": "‎ China",
    "Guaranteed software updates until\n                                    ‏": "‎ unknown"
  },
  "date_first_available_from_details": "‎ 4 Jun. 2018",
  "manufacturer_from_details": "‎ Jeylly",
  "prime_eligible": true,
  "fulfilled_by_amazon": true,
  "seller_info_text": "JeyllyMall",
  "sold_by_amazon": false,
  "rating": 4.2,
  "review_count": 2081,
  "availability_text": "Only 10 left in stock.",
  "in_stock": true,
  "features": [
    "iPhone 5s Case, High Quality Polycarbonate And TPU Material With 3 Vibrant Fashion Colors Rugged Hybrid Case, Perfectly Fit Apple iPhone 5/5s/SE Vodafone, O2, EE, Three, Giffgaff International Unlocked All Carriers",
    "iPhone SE Case Cover, Provides Basic Protection for Four Corners of Your Apple iPhone SE, Anti-Slip & Extra Grip - Skid-Proof Back Texture Provides Extra Grip, Which Can Prevent The Phone From Drop Or Fall",
    "Case for iPhone 5s, Light Weight,Stylish, Impact 3 Colors,Every Detail is Built for Beauty. Easily to Remove and Install, Without Damaging or Scratching the Phone Body",
    "iPhone 5 Skin Protector, Raised Lip For Screen Protection For Your Apple iPhone 5, Keep it Away from Scratches and Impact",
    "iPhone 5S Phone Case,Full Access To User Interface, Camera Lens, Headphone Jack, Speakerphone And Microphone, Ergonomic Grip Designed For a Secure Yet Comfortable Grip Of Your iPhone 5s"
  ],
  "description": "Product Description iPhone SE Case iPhone SE Case iPhone SE Case iPhone SE Case Buying Options Add To Basket Add To Basket Buying Options Customer Reviews 4.2 out of 5 stars 2,081 4.2 out of 5 stars 2,081 4.1 out of 5 stars 765 4.4 out of 5 stars 313 Price — no data £9.99 £ 9 . 99 £10.99 £ 10 . 99 — no data Phone Model iPhone SE 2016, iPhone 5S, iPhone 5 iPhone SE 2016, iPhone 5S, iPhone 5 iPhone SE 2016, iPhone 5S, iPhone 5 iPhone SE 2016, iPhone 5S, iPhone 5 Material TPU+PC TPU+PC TPU+PC TPU+PC Package 1* Case 1* Case, 2*Glass Screen Protector 1* Case, 2*Glass Screen Protector 1* Case, 2*Glass Screen Protector Dual Layer Design ✓ ✓ ✓ ✓",
  "selleramp": {
    "status": "SellerAmp extraction disabled"
  },
  "keepa": {
    "status": "Extraction process completed",
    "sales_rank_details_table": {
      "main_cat_current_rank": 147009,
      "main_cat_name": "Mobile Phone Basic Cases 4"
    },
    "ai_graph_analysis_status": "Keepa Graph AI Analysis disabled",
    "product_details_tab_data": {
      "Title": "Jeylly for iPhone 5/5S/SE Case, [3 Color] Slim Hybrid Impact Rugged Soft TPU & Hard PC Bumper Shockproof Protective Anti-slip Case Cover Shell for iPhone 5/5s/SE - Green",
      "Reviews - Rating": 4.2,
      "Reviews - Rating Count": 2.0,
      "Last Price Change": "9 days ago",
      "Buy Box Seller": "JeyllyMall (100% positive over last 12 months)",
      "Lowest FBA Seller": "JeyllyMall (100% positive over last 12 months)",
      "FBA Pick&Pack Fee": 1.46,
      "Referral Fee %": "14.99 %",
      "Referral Fee based on current Buy Box price": 1.28,
      "Buy Box Used Seller": "JeyllyMall (100% positive over last 12 months)",
      "Buy Box Used: Condition": "Used - Like New",
      "Total Offer Count": "2",
      "Tracking since": "2018/07/27",
      "Listed since": "2018/06/04",
      "Categories - Root": "Electronics & Photo",
      "Categories - Sub": "Basic Cases",
      "Categories - Tree": "Electronics & Photo › Mobile Phones & Communication › Accessories › Cases & Covers › Basic Cases",
      "Website Display Group - Name": "CE",
      "ASIN": "B06Y36ZVPZ",
      "Product Codes - PartNumber": "005-01010053GR",
      "Parent ASIN": "B07K1LYFKC",
      "Variation ASINs": "B06Y3JLXWY, B0CRKWNSGF, B06Y36ZVPZ, B06Y3JB9CV, B06Y37H3BT, B06Y37PTQL, B0CRKX8TN3, B0CRKVZ41Q, B0CRKR5DGB, B0CRKWJ6Q3, B0CRKWKJ7N, B0CRKW2TJJ",
      "Freq. Bought Together": "B018P3KPNA",
      "Type": "CELLULAR_PHONE_CASE",
      "Manufacturer": "Jeylly",
      "Brand": "Jeylly",
      "Product Group": "Electronics",
      "Model": "5/5S/SE 2016",
      "Color": "Green",
      "Size": "For iPhone SE/5S",
      "Pattern": "Solid",
      "Style": "Phone Skin",
      "Material": "Thermoplastic Polyurethane",
      "Binding": "Wireless Phone Accessory",
      "Package - Dimension (cm³)": "15.5 x 10.2 x 1.3 cm (= 206 cm³ )",
      "Package - Weight (g)": "18",
      "Package - Quantity": "1",
      "Item - Dimension (cm³)": "14.7 x 5.8 x 0.8 cm (= 68 cm³ )"
    }
  },
  "sales_rank": 147009,
  "category": "Mobile Phone Basic Cases 4",
  "sales_rank_source": "Keepa_SalesRankDetailsTable",
  "estimated_monthly_sales_from_bsr": 5,
  "asin_extracted_from_page": "B06Y36ZVPZ",
  "asin_queried": "B06Y36ZVPZ",
  "asin": "B06Y36ZVPZ"
}