{
  "asin_from_details": "B0DP79NZ2Q",
  "title": "DIY Explosion Gift Box explos,5 Layer Snack Explosion Box，Explosion Gift Box explos,Creative Explosion Box For Gift, Wedding Birthday Valentine Anniversary Christmas Festival (Blue)",
  "current_price": 13.99,
  "main_image": "https://m.media-amazon.com/images/W/MEDIAX_1215821-T2/images/I/71Q-8pIDg5L._AC_SL1500_.jpg",
  "thumbnails": [
    "https://m.media-amazon.com/images/W/MEDIAX_1215821-T2/images/I/41fDP91RAhL._SL1500_.jpg",
    "https://m.media-amazon.com/images/W/MEDIAX_1215821-T2/images/I/41vhsSFKIjL._SL1500_.jpg",
    "https://m.media-amazon.com/images/W/MEDIAX_1215821-T2/images/I/51i48ZdTLtL._SL1500_.jpg",
    "https://m.media-amazon.com/images/W/MEDIAX_1215821-T2/images/I/51AJJMDLfsL._SL1500_.jpg",
    "https://m.media-amazon.com/images/W/MEDIAX_1215821-T2/images/I/51e4vRjaPJL._SL1500_.jpg",
    "https://m.media-amazon.com/images/W/MEDIAX_1215821-T2/images/I/51XMJy-k8aL._SL1500_.jpg",
    "https://m.media-amazon.com/images/W/MEDIAX_1215821-T2/images/I/51MHg4RcjxL._SL1500_.jpg"
  ],
  "high_res_gallery": [],
  "amazon_product_details_section": {
    "Package Dimensions\n                                    ‏\n                                    :\n                                    ‎": "22.3 x 21.3 x 6 cm; 500 g",
    "Date First Available\n                                    ‏\n                                    :\n                                    ‎": "28 Nov. 2024",
    "Manufacturer\n                                    ‏\n                                    :\n                                    ‎": "MRUVTC",
    "ASIN\n                                    ‏\n                                    :\n                                    ‎": "B0DP79NZ2Q",
    "Manufacturer reference\n                                    ‏\n                                    :\n                                    ‎": "Gift Box 001",
    "Country of origin\n                                    ‏\n                                    :\n                                    ‎": "China",
    "Customer reviews": "5.0 5.0 out of 5 stars (4) var dpAcrHasRegisteredArcLinkClickAction; P.when('A', 'ready').execute(function(A) { if (dpAcrHasRegisteredArcLinkClickAction !== true) { dpAcrHasRegisteredArcLinkClickAction = true; A.declarative( 'acrLink-click-metrics', 'click', { \"allowLinkDefault\": true }, function (event) { if (window.ue) { ue.count(\"acrLinkClickCount\", (ue.count(\"acrLinkClickCount\") || 0) + 1); } } ); } }); P.when('A', 'cf').execute(function(A) { A.declarative('acrStarsLink-click-metrics', 'click', { \"allowLinkDefault\" : true }, function(event){ if(window.ue) { ue.count(\"acrStarsLinkWithPopoverClickCount\", (ue.count(\"acrStarsLinkWithPopoverClickCount\") || 0) + 1); } }); });",
    "Package Dimensions\n                                    ‏": "‎ 22.3 x 21.3 x 6 cm; 500 g",
    "Date First Available\n                                    ‏": "‎ 28 Nov. 2024",
    "Manufacturer\n                                    ‏": "‎ MRUVTC",
    "ASIN\n                                    ‏": "‎ B0DP79NZ2Q",
    "Manufacturer reference\n                                    ‏": "‎ Gift Box 001",
    "Country of origin\n                                    ‏": "‎ China"
  },
  "dimensions_from_details": "‎ 22.3 x 21.3 x 6 cm; 500 g",
  "date_first_available_from_details": "‎ 28 Nov. 2024",
  "manufacturer_from_details": "‎ Gift Box 001",
  "prime_eligible": true,
  "fulfilled_by_amazon": false,
  "seller_info_text": "PASCOAL MAQUERO MACHAIRE LIMITED",
  "sold_by_amazon": false,
  "rating": 5.0,
  "review_count": 4,
  "availability_text": "In stock",
  "in_stock": true,
  "features": [
    "1. [Unique design] : This DIY explosion gift box features a carefully designed 5-level structure, each level is like a mysterious little world waiting to be explored. When the recipient opens the gift box, it will \"explode\" like a blooming flower, showing a wealth of surprises inside, this unique way of opening will make the other party's eyes shine, become a special day unforgettable beautiful moment",
    "2. [Versatile] : Whether it is an anniversary, birthday, Valentine's Day or wedding, it is an excellent gift choice. Use it as a romantic surprise for your partner, as a birthday gift for a friend, or as a special gift at a wedding to show your heart and add unique meaning to every important moment",
    "3. [Creativity and interaction] : As a creative explosion gift box, it gives you full DIY space. Like a fine scrapbook, you can arrange photos, handwritten wishes, trinkets and more on each layer, incorporating your own creativity and emotion. In addition, during the assembly process, you can also enjoy the hands-on fun with family and friends, adding more warm memories to the gift",
    "4. [Excellent quality] : The gift box is made of high-quality materials, and the paper is tough and thick, which can not only ensure the stability of the gift box, so that it can be perfectly presented when opened, but also can be preserved for a long time. Every level of detail is designed to ensure that the gift not only looks amazing, but also feels great, showing your taste and the importance of the recipient",
    "5. [Super value match] : This gift box is specially designed as a snack explosion box, you can fill it with a variety of delicious snacks, so that the recipient can enjoy the pleasure of taste buds while harvesting surprises. The value combination of snacks and creative gift boxes brings double the happiness of each other, which is a fun and realistic gift, and the price is very high"
  ],
  "description": "This 5-layer DIY exploding gift box offers excellent quality, creative space and interactive fun, suitable for anniversaries, birthdays and many other occasions, with snacks to bring double happiness, is the perfect gift to express your heart. Material :paper Color:Red, blue, pink Packaging includes :DIY Explosion Gift Box Note: Manual measurement, please allow a slight error in size. There may be slight differences in color due to different screens.",
  "selleramp": {
    "status": "SellerAmp extraction disabled"
  },
  "keepa": {
    "status": "Extraction process completed",
    "sales_rank_details_table": {
      "main_cat_current_rank": 56744,
      "main_cat_name": "Stationery & Office Supplies 2.3 drops / month",
      "sub_cat_current_rank": 385,
      "sub_cat_name": "Gift Boxes 4"
    },
    "ai_graph_analysis_status": "Keepa Graph AI Analysis disabled",
    "product_details_tab_data": {
      "Title": "DIY Explosion Gift Box explos,5 Layer Snack Explosion Box，Explosion Gift Box explos,Creative Explosion Box For Gift, Wedding Birthday Valentine Anniversary Christmas Festival (Blue)",
      "Sales Rank - Reference": "Stationery & Office Supplies",
      "Sales Rank - Display Group": "office_product_display_on_website",
      "Reviews - Rating": 5.0,
      "Reviews - Rating Count": 4.0,
      "Last Price Change": "2 months ago",
      "Buy Box Seller": "PASCOAL MAQUERO MACHAIRE LIMITED (98% positive over last 12 months)",
      "Lowest FBA Seller": "PASCOAL MAQUERO MACHAIRE LIMITED (98% positive over last 12 months)",
      "FBA Pick&Pack Fee": 2.94,
      "Referral Fee %": "15 %",
      "Referral Fee based on current Buy Box price": 2.1,
      "Total Offer Count": "1",
      "Tracking since": "2025/01/04",
      "Listed since": "2024/11/28",
      "Categories - Root": "Stationery & Office Supplies",
      "Categories - Sub": "Gift Boxes",
      "Categories - Tree": "Stationery & Office Supplies › Envelopes & Mailing Supplies › Packing Materials › Gift Wrapping Supplies › Gift Boxes",
      "Website Display Group - Name": "Single Detail Page Misc",
      "ASIN": "B0DP79NZ2Q",
      "Product Codes - UPC": "752804808169",
      "Product Codes - EAN": "0752804808169",
      "Product Codes - PartNumber": "Gift Box 001",
      "Parent ASIN": "B0DP8CQS7Q",
      "Variation ASINs": "B0DP79NZ2Q, B0DP7C54V6, B0DP79RD4R",
      "Freq. Bought Together": "B0872ZYZ8B, B0CQNZKLGN",
      "Type": "GIFT_WRAP",
      "Manufacturer": "MRUVTC",
      "Brand": "MRUVTC",
      "Product Group": "Drugstore",
      "Color": "Blue",
      "Unit Details - Unit Value": "1",
      "Unit Details - Unit Type": "gram",
      "Item Form": "Box",
      "Pattern": "Solid",
      "Material": "Paper",
      "Number of Items": "1",
      "Package - Dimension (cm³)": "22.3 x 21.3 x 6.0 cm (= 2,850 cm³ )",
      "Package - Weight (g)": "500",
      "Included Components": "Box"
    }
  },
  "eans_on_page": [
    "0752804808169"
  ],
  "ean_on_page_source": "Keepa_Product_Details",
  "ean_on_page": "0752804808169",
  "sales_rank": 56744,
  "category": "Stationery & Office Supplies 2.3",
  "sales_rank_source": "Keepa_SalesRankDetailsTable",
  "estimated_monthly_sales_from_bsr": 10,
  "asin_extracted_from_page": "B0DP79NZ2Q",
  "asin_queried": "B0DP79NZ2Q",
  "asin": "B0DP79NZ2Q"
}