{
  "asin_from_details": "B006WNE3ZW",
  "title": "Keep-It-Handy 2 x 10g Unscented Stain Remover Pac",
  "current_price": 6.45,
  "main_image": "https://m.media-amazon.com/images/W/MEDIAX_1215821-T2/images/I/5170ZmH8sTL._AC_SY450_.jpg",
  "thumbnails": [
    "https://m.media-amazon.com/images/W/MEDIAX_1215821-T2/images/I/5170ZmH8sTL._SL1500_.jpg"
  ],
  "high_res_gallery": [],
  "amazon_product_details_section": {
    "ASIN": "B006WNE3ZW",
    "Date First Available": "28 Sept. 2012"
  },
  "date_first_available_from_details": "28 Sept. 2012",
  "prime_eligible": true,
  "fulfilled_by_amazon": false,
  "seller_info_text": "V-VAPE",
  "sold_by_amazon": false,
  "rating": 5.0,
  "review_count": 8,
  "availability_text": "Only 9 left in stock.",
  "in_stock": true,
  "features": [
    "Versatile Stain Removal: Tackles a wide range of stains on all fabric types",
    "Convenient Packaging: 2 x 10g pacs for easy dosing and storage",
    "Unscented Formula: Gentle on sensitive skin and ideal for those with allergies",
    "Eco-Friendly: Regular formulation with no harsh chemicals, suitable for septic tanks",
    "Keep-It-Handy Quality: Trusted brand ensuring effective stain removal and customer satisfaction"
  ],
  "description": "Experience the convenience of our 2-pack Keep-It-Handy Unscented Stain Remover Pacs, each containing 10 grams of powerful, regular formulation stain-fighting power. Ideal for all skin types and fabrics, these unscented, laundry detergent pacs are perfect for those with sensitivities or preferences for fragrance-free products. Each pac is designed to tackle specific stains, making laundry day a breeze. Keep your whites white and colors vibrant with our effective, easy-to-use stain remover pacs.",
  "specifications_table": {
    "Brand": "‎Keep-It-Handy",
    "Item Weight": "‎10 g"
  },
  "selleramp": {
    "status": "SellerAmp extraction disabled"
  },
  "keepa": {
    "status": "Extraction process completed",
    "sales_rank_details_table": {
      "main_cat_current_rank": 187865,
      "main_cat_name": "Grocery 0.3 drops / month",
      "sub_cat_current_rank": 1184,
      "sub_cat_name": "Stain Removers 3"
    },
    "ai_graph_analysis_status": "Keepa Graph AI Analysis disabled",
    "product_details_tab_data": {
      "Title": "Keep-It-Handy 2 x 10g Unscented Stain Remover Pac",
      "Sales Rank - Reference": "Grocery",
      "Sales Rank - Display Group": "grocery_display_on_website",
      "Reviews - Rating": 5.0,
      "Reviews - Rating Count": 8.0,
      "Last Price Change": "4 months ago",
      "Buy Box Seller": "V-VAPE (86% positive over last 12 months)",
      "Lowest FBM Seller": "V-VAPE (86% positive over last 12 months) pricescrapper (82% positive over last 12 months)",
      "Total Offer Count": "2",
      "Tracking since": "2016/02/19",
      "Listed since": "2012/09/28",
      "Categories - Root": "Grocery",
      "Categories - Sub": "Stain Removers",
      "Categories - Tree": "Grocery › Home Care & Cleaning › Laundry › Stain Removers",
      "Website Display Group - Name": "Kitchen",
      "ASIN": "B006WNE3ZW",
      "Product Codes - EAN": "5055257880221",
      "Freq. Bought Together": "B07VM652M9, B07TZK427B",
      "Type": "LAUNDRY_DETERGENT",
      "Brand": "Keep-It-Handy",
      "Product Group": "Home",
      "Size": "10 g (Pack of 2)",
      "Unit Details - Unit Value": "20",
      "Unit Details - Unit Type": "gram",
      "Scent": "Unscented",
      "Item Form": "Pac",
      "Specific Uses": "Stain Remover",
      "Binding": "Kitchen & Home",
      "Number of Items": "2",
      "Package - Quantity": "2",
      "Item - Model (g)": "10",
      "Hazardous Materials": "Transportation Regulatory Class: 9"
    }
  },
  "eans_on_page": [
    "5055257880221"
  ],
  "ean_on_page_source": "Keepa_Product_Details",
  "ean_on_page": "5055257880221",
  "sales_rank": 187865,
  "category": "Grocery 0.3",
  "sales_rank_source": "Keepa_SalesRankDetailsTable",
  "estimated_monthly_sales_from_bsr": 10,
  "asin_extracted_from_page": "B006WNE3ZW",
  "asin_queried": "B006WNE3ZW",
  "asin": "B006WNE3ZW"
}